<?xml version="1.0" encoding="UTF-8"?><record_update table="sn_cmdb_int_util_duplicate_row_rule">
    <sn_cmdb_int_util_duplicate_row_rule action="INSERT_OR_UPDATE">
        <active>true</active>
        <advanced_settings>false</advanced_settings>
        <data_source display_value="Cisco ISE pxGrid Session Data">c81a55ae972d7950bd8ff0021153afa2</data_source>
        <ignore_fields>timestamp,row,sys_import_row,u_timestamp</ignore_fields>
        <sys_class_name>sn_cmdb_int_util_duplicate_row_rule</sys_class_name>
        <sys_created_by>jamie@moderncyber.com</sys_created_by>
        <sys_created_on>2023-10-13 01:32:30</sys_created_on>
        <sys_id>0662ffd297f9fd90bd8ff0021153af5b</sys_id>
        <sys_mod_count>3</sys_mod_count>
        <sys_name>c81a55ae972d7950bd8ff0021153afa2</sys_name>
        <sys_package display_value="Cisco ISE" source="x_caci_cisco_ise">094d27ca97213950bd8ff0021153af4a</sys_package>
        <sys_policy/>
        <sys_scope display_value="Cisco ISE">094d27ca97213950bd8ff0021153af4a</sys_scope>
        <sys_update_name>sn_cmdb_int_util_duplicate_row_rule_0662ffd297f9fd90bd8ff0021153af5b</sys_update_name>
        <sys_updated_by>jamie@moderncyber.com</sys_updated_by>
        <sys_updated_on>2023-10-13 01:57:57</sys_updated_on>
    </sn_cmdb_int_util_duplicate_row_rule>
</record_update>
